pylint_flask_sqlalchemy/__init__.py
tests/__init__.py
tests/example.py
tests/test_plugin.py
pylint_flask_sqlalchemy-0.2.0.dist-info/LICENSE
pylint_flask_sqlalchemy-0.2.0.dist-info/METADATA
pylint_flask_sqlalchemy-0.2.0.dist-info/WHEEL
pylint_flask_sqlalchemy-0.2.0.dist-info/top_level.txt
pylint_flask_sqlalchemy-0.2.0.dist-info/RECORD
