Metadata-Version: 2.1
Name: pylint-flask-sqlalchemy
Version: 0.2.0
Summary: A Pylint plugin for improving code analysis when editing code using Flask-SQLAlchemy
Home-page: https://gitlab.anybox.cloud/rboyer/pylint_flask_sqlalchemy
Author: Anybox
Author-email: rboyer@anybox.fr
Maintainer: Renaud Boyer
Maintainer-email: rboyer@anybox.fr
License: GPL
Project-URL: Bug Tracker, https://gitlab.anybox.cloud/rboyer/pylint_flask_sqlalchemy/issues
Project-URL: Documentation, https://gitlab.anybox.cloud/rboyer/pylint_flask_sqlalchemy
Project-URL: Source Code, https://gitlab.anybox.cloud/rboyer/pylint_flask_sqlalchemy
Platform: any
Classifier: Development Status :: 3 - Alpha
Classifier: Intended Audience :: Developers
Classifier: Operating System :: OS Independent
Classifier: Programming Language :: Python :: 3 :: Only
Classifier: License :: OSI Approved :: GNU General Public License (GPL)
Classifier: Typing :: Typed
Requires-Python: >=3.5
Provides-Extra: dev
